ezstitcher/__init__.py
ezstitcher/__main__.py
ezstitcher/core/__init__.py
ezstitcher/core/abstract_step.py
ezstitcher/core/config.py
ezstitcher/core/file_system_manager.py
ezstitcher/core/focus_analyzer.py
ezstitcher/core/image_processor.py
ezstitcher/core/main.py
ezstitcher/core/microscope_interfaces.py
ezstitcher/core/opera_phenix_xml_parser.py
ezstitcher/core/pipeline.py
ezstitcher/core/pipeline_base.py
ezstitcher/core/pipeline_factories.py
ezstitcher/core/pipeline_orchestrator.py
ezstitcher/core/steps.py
ezstitcher/core/stitcher.py
ezstitcher/core/utils.py
ezstitcher/ez/__init__.py
ezstitcher/ez/core.py
ezstitcher/ez/functions.py
ezstitcher/ez/utils.py
ezstitcher/microscopes/__init__.py
ezstitcher/microscopes/imagexpress.py
ezstitcher/microscopes/opera_phenix.py
ezstitcher/tests/__init__.py
ezstitcher/tests/generators/__init__.py
ezstitcher/tests/generators/generate_synthetic_data.py
ezstitcher-1.1.0.dist-info/METADATA
ezstitcher-1.1.0.dist-info/WHEEL
ezstitcher-1.1.0.dist-info/top_level.txt
ezstitcher-1.1.0.dist-info/RECORD
