Metadata-Version: 2.4
Name: ezstitcher
Version: 1.1.0
Summary: An easy-to-use microscopy image stitching and processing tool
Home-page: https://github.com/trissim/ezstitcher
Author: trissim
Author-email: tristan.simas@mail.mcgill.ca
Classifier: Programming Language :: Python :: 3
Classifier: Programming Language :: Python :: 3.11
Classifier: License :: OSI Approved :: MIT License
Classifier: Operating System :: OS Independent
Requires-Python: ~=3.11.0
Requires-Dist: numpy>=1.20.0
Requires-Dist: scikit-image>=0.18.0
Requires-Dist: scipy>=1.6.0
Requires-Dist: pandas>=1.2.0
Requires-Dist: imageio>=2.9.0
Requires-Dist: tifffile>=2021.1.1
Requires-Dist: imagecodecs>=2021.1.1
Requires-Dist: ashlar>=1.14.0
Requires-Dist: opencv-python>=4.5.0
Requires-Dist: PyYAML>=6.0
Provides-Extra: dev
Requires-Dist: pytest==7.4.0; extra == "dev"
Requires-Dist: pytest-cov==4.1.0; extra == "dev"
Requires-Dist: coverage==7.3.2; extra == "dev"
Requires-Dist: genbadge[coverage]; extra == "dev"
Requires-Dist: sphinx; extra == "dev"
Requires-Dist: sphinx-rtd-theme; extra == "dev"
Requires-Dist: black; extra == "dev"
Requires-Dist: flake8; extra == "dev"
Dynamic: author
Dynamic: author-email
Dynamic: classifier
Dynamic: description
Dynamic: description-content-type
Dynamic: home-page
Dynamic: provides-extra
Dynamic: requires-dist
Dynamic: requires-python
Dynamic: summary
